pyqubits/__init__.py
pyqubits/gates.py
pyqubits/quantumstate.py
pyqubits/utils.py
pyqubits-0.2.1.dist-info/LICENSE
pyqubits-0.2.1.dist-info/METADATA
pyqubits-0.2.1.dist-info/WHEEL
pyqubits-0.2.1.dist-info/top_level.txt
pyqubits-0.2.1.dist-info/RECORD
