Metadata-Version: 2.1
Name: pyqubits
Version: 0.2.1
Author: Thomas Brier
License-File: LICENSE
Requires-Dist: numpy
Requires-Dist: numba
